{
  "storeId": "112",
  "deviceId": "SCOUTPI-0012",
  "timestamp": "",
  "transactionId": "b1539c5c-827b-4469-bf7a-cf2ce58b289f",
  "brandDetection": {
    "detectedBrands": {
      "Rejoice": 0.67,
      "Pantene": 0.77,
      "Close Up": 0.444
    },
    "explicitMentions": [
      {
        "brand": "Rejoice",
        "category": "Hair Care",
        "subcategory": "unspecified",
        "confidence": 0.67,
        "detection_type": "exact_match",
        "context": "tatlo rejoiceng pantene, maliit close"
      },
      {
        "brand": "Pantene",
        "category": "Hair Care",
        "subcategory": "shampoo",
        "confidence": 0.77,
        "detection_type": "exact_match",
        "context": "tatlo rejoiceng pantene, maliit close isa"
      },
      {
        "brand": "Close Up",
        "category": "Oral Care",
        "subcategory": "unspecified",
        "confidence": 0.444,
        "detection_type": "exact_match",
        "context": "tatlo rejoiceng pantene, maliit close isa up"
      }
    ],
    "implicitSignals": [],
    "detectionMethods": [
      "exact_match"
    ],
    "categoryBrandMapping": {
      "Hair Care": {
        "branded": [
          {
            "brand": "Rejoice",
            "confidence": 0.67,
            "quantity": 1
          },
          {
            "brand": "Pantene",
            "confidence": 0.77,
            "quantity": 3
          }
        ],
        "unbranded_volume": 0
      },
      "Oral Care": {
        "branded": [
          {
            "brand": "Close Up",
            "confidence": 0.444,
            "quantity": 1
          }
        ],
        "unbranded_volume": 0
      }
    }
  },
  "items": [
    {
      "brandName": "Pantene",
      "productName": "Pantene Conditioner",
      "genericName": "Product",
      "localName": "shampoo",
      "sku": "PANTENE-CONDITIONER-180ML",
      "quantity": 3,
      "unit": "pc",
      "unitPrice": 135.0,
      "totalPrice": 405.0,
      "category": "Hair Care",
      "isUnbranded": false,
      "isBulk": false,
      "detectionMethod": "stt_brand_only",
      "confidence": 0.77,
      "brandConfidence": 0.82,
      "suggestedBrands": null,
      "notes": "STT: 'tatlo rejoiceng pantene, maliit close isa'",
      "customerRequest": {
        "requestType": "branded",
        "specificBrand": true,
        "pointedToProduct": false,
        "acceptedSuggestion": false
      }
    },
    {
      "brandName": "Close Up",
      "productName": "Close Up Ever Fresh Red Hot",
      "genericName": "Product",
      "localName": "toothpaste",
      "sku": "CLOSE-UP-RED-145G",
      "quantity": 1,
      "unit": "pc",
      "unitPrice": 75.0,
      "totalPrice": 75.0,
      "category": "Oral Care",
      "isUnbranded": false,
      "isBulk": false,
      "detectionMethod": "stt_brand_only",
      "confidence": 0.444,
      "brandConfidence": 0.627,
      "suggestedBrands": null,
      "notes": "STT: 'tatlo rejoiceng pantene, maliit close isa up'",
      "customerRequest": {
        "requestType": "branded",
        "specificBrand": true,
        "pointedToProduct": false,
        "acceptedSuggestion": false
      }
    }
  ],
  "totals": {
    "totalAmount": 480.0,
    "totalItems": 4,
    "brandedAmount": 480.0,
    "unbrandedAmount": 0.0,
    "brandedCount": 4,
    "unbrandedCount": 0,
    "uniqueBrandsCount": 2
  },
  "transactionContext": {
    "duration": 6.0,
    "paymentMethod": "cash",
    "timeOfDay": "unspecified",
    "dayType": "weekday",
    "audioTranscript": "tatlo rejoiceng pantene, maliit close isa up",
    "processingMethods": [
      "stt_transcription",
      "brand_detection",
      "fuzzy_matching",
      "pricing_lookup",
      "totals_calculation",
      "confidence_scoring"
    ]
  },
  "privacy": {
    "audioStored": false,
    "brandAnalysisOnly": true,
    "noFacialRecognition": true,
    "noImageProcessing": true,
    "dataRetentionDays": 30,
    "anonymizationLevel": "high",
    "consentTimestamp": "2025-09-12T23:20:50.898882.000Z"
  },
  "processingTime": 15.87,
  "edgeVersion": "v2.0.0-stt-only"
}