{
  "storeId": "108",
  "deviceId": "SCOUTPI-0006",
  "timestamp": "",
  "transactionId": "089c2aaa-fa08-4311-96bd-997c93d2ec8d",
  "brandDetection": {
    "detectedBrands": {
      "Globe": 0.95,
      "Sprite": 0.95
    },
    "explicitMentions": [
      {
        "brand": "Globe",
        "category": "Services",
        "subcategory": "unspecified",
        "confidence": 0.95,
        "detection_type": "exact_match",
        "context": "smart load po globe isa dalawang sachet"
      },
      {
        "brand": "Sprite",
        "category": "Non-Alcoholic",
        "subcategory": "lemon_lime_soda",
        "confidence": 0.95,
        "detection_type": "exact_match",
        "context": "isa dalawang sachet sprite"
      }
    ],
    "implicitSignals": [],
    "detectionMethods": [
      "exact_match"
    ],
    "categoryBrandMapping": {
      "Services": {
        "branded": [
          {
            "brand": "Globe",
            "confidence": 0.95,
            "quantity": 3
          }
        ],
        "unbranded_volume": 0
      },
      "Non-Alcoholic": {
        "branded": [
          {
            "brand": "Sprite",
            "confidence": 0.95,
            "quantity": 3
          }
        ],
        "unbranded_volume": 0
      }
    }
  },
  "items": [
    {
      "brandName": "Globe",
      "productName": "Globe Load 100",
      "genericName": "Product",
      "localName": "globe",
      "sku": "GLOBE-LOAD-100",
      "quantity": 3,
      "unit": "pc",
      "unitPrice": 100.0,
      "totalPrice": 300.0,
      "category": "Services",
      "isUnbranded": false,
      "isBulk": false,
      "detectionMethod": "stt_brand_only",
      "confidence": 0.95,
      "brandConfidence": 0.85,
      "suggestedBrands": null,
      "notes": "STT: 'smart load po globe isa dalawang sachet'",
      "customerRequest": {
        "requestType": "unbranded",
        "specificBrand": true,
        "pointedToProduct": false,
        "acceptedSuggestion": false
      }
    },
    {
      "brandName": "Sprite",
      "productName": "Sprite 1.5L",
      "genericName": "Product",
      "localName": "sprite",
      "sku": "SPRITE-1.5L",
      "quantity": 3,
      "unit": "pc",
      "unitPrice": 79.0,
      "totalPrice": 237.0,
      "category": "Non-Alcoholic",
      "isUnbranded": false,
      "isBulk": false,
      "detectionMethod": "stt_brand_only",
      "confidence": 0.95,
      "brandConfidence": 0.85,
      "suggestedBrands": null,
      "notes": "STT: 'isa dalawang sachet sprite'",
      "customerRequest": {
        "requestType": "branded",
        "specificBrand": true,
        "pointedToProduct": false,
        "acceptedSuggestion": false
      }
    }
  ],
  "totals": {
    "totalAmount": 537.0,
    "totalItems": 6,
    "brandedAmount": 537.0,
    "unbrandedAmount": 0.0,
    "brandedCount": 6,
    "unbrandedCount": 0,
    "uniqueBrandsCount": 2
  },
  "transactionContext": {
    "duration": 6.0,
    "paymentMethod": "cash",
    "timeOfDay": "unspecified",
    "dayType": "weekend",
    "audioTranscript": "smart load po globe isa dalawang sachet sprite",
    "processingMethods": [
      "stt_transcription",
      "brand_detection",
      "fuzzy_matching",
      "pricing_lookup",
      "totals_calculation",
      "confidence_scoring"
    ]
  },
  "privacy": {
    "audioStored": false,
    "brandAnalysisOnly": true,
    "noFacialRecognition": true,
    "noImageProcessing": true,
    "dataRetentionDays": 30,
    "anonymizationLevel": "high",
    "consentTimestamp": "2025-09-14T17:26:09.292135.000Z"
  },
  "processingTime": 10.89,
  "edgeVersion": "v2.0.0-stt-only"
}