{
  "storeId": "108",
  "deviceId": "SCOUTPI-0006",
  "timestamp": "",
  "transactionId": "27875891-72bf-418c-97d8-79eeb60d0354",
  "brandDetection": {
    "detectedBrands": {
      "Bear Brand": 0.77,
      "Sprite": 0.77
    },
    "explicitMentions": [
      {
        "brand": "Bear Brand",
        "category": "unspecified",
        "subcategory": "unspecified",
        "confidence": 0.77,
        "detection_type": "exact_match",
        "context": "Bear Brand isa sige dalawa Sprite"
      },
      {
        "brand": "Sprite",
        "category": "Non-Alcoholic",
        "subcategory": "lemon_lime_soda",
        "confidence": 0.77,
        "detection_type": "exact_match",
        "context": "isa sige dalawa Sprite"
      }
    ],
    "implicitSignals": [],
    "detectionMethods": [
      "exact_match"
    ],
    "categoryBrandMapping": {
      "unspecified": {
        "branded": [
          {
            "brand": "Bear Brand",
            "confidence": 0.77,
            "quantity": 3
          }
        ],
        "unbranded_volume": 0
      },
      "Non-Alcoholic": {
        "branded": [
          {
            "brand": "Sprite",
            "confidence": 0.77,
            "quantity": 3
          }
        ],
        "unbranded_volume": 0
      }
    }
  },
  "items": [
    {
      "brandName": "Bear Brand",
      "productName": "Bear Brand Junior Milk 150g",
      "genericName": "Product",
      "localName": "sprite",
      "sku": "BEAR-BRAND-JUNIOR-150G",
      "quantity": 3,
      "unit": "pc",
      "unitPrice": 68.5,
      "totalPrice": 205.5,
      "category": "Pantry Staples & Groceries",
      "isUnbranded": false,
      "isBulk": false,
      "detectionMethod": "stt_brand_only",
      "confidence": 0.77,
      "brandConfidence": 0.76,
      "suggestedBrands": null,
      "notes": "STT: 'Bear Brand isa sige dalawa Sprite'",
      "customerRequest": {
        "requestType": "branded",
        "specificBrand": true,
        "pointedToProduct": false,
        "acceptedSuggestion": false
      }
    },
    {
      "brandName": "Sprite",
      "productName": "Sprite 1.5L",
      "genericName": "Product",
      "localName": "sprite",
      "sku": "SPRITE-1.5L",
      "quantity": 3,
      "unit": "pc",
      "unitPrice": 79.0,
      "totalPrice": 237.0,
      "category": "Non-Alcoholic",
      "isUnbranded": false,
      "isBulk": false,
      "detectionMethod": "stt_brand_only",
      "confidence": 0.77,
      "brandConfidence": 0.76,
      "suggestedBrands": null,
      "notes": "STT: 'isa sige dalawa Sprite'",
      "customerRequest": {
        "requestType": "branded",
        "specificBrand": true,
        "pointedToProduct": false,
        "acceptedSuggestion": false
      }
    }
  ],
  "totals": {
    "totalAmount": 442.5,
    "totalItems": 6,
    "brandedAmount": 442.5,
    "unbrandedAmount": 0.0,
    "brandedCount": 6,
    "unbrandedCount": 0,
    "uniqueBrandsCount": 2
  },
  "transactionContext": {
    "duration": 11.34,
    "paymentMethod": "cash",
    "timeOfDay": "unspecified",
    "dayType": "weekend",
    "audioTranscript": "Bear Brand isa sige dalawa Sprite",
    "processingMethods": [
      "stt_transcription",
      "brand_detection",
      "fuzzy_matching",
      "pricing_lookup",
      "totals_calculation",
      "confidence_scoring"
    ]
  },
  "privacy": {
    "audioStored": false,
    "brandAnalysisOnly": true,
    "noFacialRecognition": true,
    "noImageProcessing": true,
    "dataRetentionDays": 30,
    "anonymizationLevel": "high",
    "consentTimestamp": "2025-09-14T13:09:34.162772.000Z"
  },
  "processingTime": 9.8,
  "edgeVersion": "v2.0.0-stt-only"
}