{
  "storeId": "108",
  "deviceId": "SCOUTPI-0006",
  "timestamp": "",
  "transactionId": "386c356c-f714-4d1c-a3c1-d62a44c368a2",
  "brandDetection": {
    "detectedBrands": {
      "Dole": 0.83,
      "Ovaltine": 0.83
    },
    "explicitMentions": [
      {
        "brand": "Dole",
        "category": "Canned & Jarred Goods",
        "subcategory": "unspecified",
        "confidence": 0.83,
        "detection_type": "exact_match",
        "context": "extra joss po dole isa juice dalawa"
      },
      {
        "brand": "Ovaltine",
        "category": "unspecified",
        "subcategory": "unspecified",
        "confidence": 0.83,
        "detection_type": "exact_match",
        "context": "isa juice dalawa ovaltine please"
      }
    ],
    "implicitSignals": [],
    "detectionMethods": [
      "exact_match"
    ],
    "categoryBrandMapping": {
      "Canned & Jarred Goods": {
        "branded": [
          {
            "brand": "Dole",
            "confidence": 0.83,
            "quantity": 1
          }
        ],
        "unbranded_volume": 0
      },
      "unspecified": {
        "branded": [
          {
            "brand": "Ovaltine",
            "confidence": 0.83,
            "quantity": 3
          }
        ],
        "unbranded_volume": 0
      }
    }
  },
  "items": [
    {
      "brandName": "Dole",
      "productName": "Dole Pineapple Juice",
      "genericName": "Product",
      "localName": "dole",
      "sku": "DOLE-PINEAPPLE-JUICE-240ML",
      "quantity": 1,
      "unit": "pc",
      "unitPrice": 27.3,
      "totalPrice": 27.3,
      "category": "Canned & Jarred Goods",
      "isUnbranded": false,
      "isBulk": false,
      "detectionMethod": "stt_brand_only",
      "confidence": 0.83,
      "brandConfidence": 0.85,
      "suggestedBrands": null,
      "notes": "STT: 'extra joss po dole isa juice dalawa'",
      "customerRequest": {
        "requestType": "branded",
        "specificBrand": true,
        "pointedToProduct": false,
        "acceptedSuggestion": false
      }
    },
    {
      "brandName": "Ovaltine",
      "productName": "Ovaltine Chocolate",
      "genericName": "Product",
      "localName": "coke",
      "sku": "OVALTINE-24G",
      "quantity": 3,
      "unit": "sachet",
      "unitPrice": 10.0,
      "totalPrice": 30.0,
      "category": "unspecified",
      "isUnbranded": false,
      "isBulk": false,
      "detectionMethod": "stt_brand_only",
      "confidence": 0.83,
      "brandConfidence": 0.79,
      "suggestedBrands": null,
      "notes": "STT: 'isa juice dalawa ovaltine please'",
      "customerRequest": {
        "requestType": "branded",
        "specificBrand": true,
        "pointedToProduct": false,
        "acceptedSuggestion": false
      }
    }
  ],
  "totals": {
    "totalAmount": 57.3,
    "totalItems": 4,
    "brandedAmount": 57.3,
    "unbrandedAmount": 0.0,
    "brandedCount": 4,
    "unbrandedCount": 0,
    "uniqueBrandsCount": 2
  },
  "transactionContext": {
    "duration": 5.76,
    "paymentMethod": "cash",
    "timeOfDay": "unspecified",
    "dayType": "weekend",
    "audioTranscript": "extra joss po dole isa juice dalawa ovaltine please",
    "processingMethods": [
      "stt_transcription",
      "brand_detection",
      "fuzzy_matching",
      "pricing_lookup",
      "totals_calculation",
      "confidence_scoring"
    ]
  },
  "privacy": {
    "audioStored": false,
    "brandAnalysisOnly": true,
    "noFacialRecognition": true,
    "noImageProcessing": true,
    "dataRetentionDays": 30,
    "anonymizationLevel": "high",
    "consentTimestamp": "2025-09-14T16:57:47.300956.000Z"
  },
  "processingTime": 9.65,
  "edgeVersion": "v2.0.0-stt-only"
}