{
  "storeId": "108",
  "deviceId": "SCOUTPI-0006",
  "timestamp": "",
  "transactionId": "3ed30eeb-9446-4e28-8256-31f3dfc5df9a",
  "brandDetection": {
    "detectedBrands": {
      "Cherry Prepaid": 0.434,
      "Chips Ahoy": 0.434
    },
    "explicitMentions": [
      {
        "brand": "Cherry Prepaid",
        "category": "Services",
        "subcategory": "unspecified",
        "confidence": 0.434,
        "detection_type": "exact_match",
        "context": "cherry dalawa prepaid yung tatlo chips isa softdri..."
      },
      {
        "brand": "Chips Ahoy",
        "category": "Biscuits & Crackers",
        "subcategory": "unspecified",
        "confidence": 0.434,
        "detection_type": "exact_match",
        "context": "cherry dalawa prepaid yung tatlo chips isa softdri..."
      }
    ],
    "implicitSignals": [],
    "detectionMethods": [
      "exact_match"
    ],
    "categoryBrandMapping": {
      "Services": {
        "branded": [
          {
            "brand": "Cherry Prepaid",
            "confidence": 0.434,
            "quantity": 3
          }
        ],
        "unbranded_volume": 0
      },
      "Biscuits & Crackers": {
        "branded": [
          {
            "brand": "Chips Ahoy",
            "confidence": 0.434,
            "quantity": 1
          }
        ],
        "unbranded_volume": 0
      }
    }
  },
  "items": [
    {
      "brandName": "Cherry Prepaid",
      "productName": "Cherry Prepaid Load 100",
      "genericName": "Product",
      "localName": "chips",
      "sku": "CHERRYPREPAID-LOAD-100",
      "quantity": 3,
      "unit": "pc",
      "unitPrice": 100.0,
      "totalPrice": 300.0,
      "category": "Services",
      "isUnbranded": false,
      "isBulk": false,
      "detectionMethod": "stt_brand_only",
      "confidence": 0.434,
      "brandConfidence": 0.622,
      "suggestedBrands": null,
      "notes": "STT: 'cherry dalawa prepaid yung tatlo chips isa softdri...'",
      "customerRequest": {
        "requestType": "branded",
        "specificBrand": true,
        "pointedToProduct": true,
        "acceptedSuggestion": false
      }
    },
    {
      "brandName": "Chips Ahoy",
      "productName": "Chips Ahoy Cookies",
      "genericName": "Product",
      "localName": "chips",
      "sku": "CHIPS-AHOY-40G",
      "quantity": 1,
      "unit": "pc",
      "unitPrice": 12.0,
      "totalPrice": 12.0,
      "category": "Biscuits & Crackers",
      "isUnbranded": false,
      "isBulk": false,
      "detectionMethod": "stt_brand_only",
      "confidence": 0.434,
      "brandConfidence": 0.622,
      "suggestedBrands": null,
      "notes": "STT: 'cherry dalawa prepaid yung tatlo chips isa softdri...'",
      "customerRequest": {
        "requestType": "branded",
        "specificBrand": true,
        "pointedToProduct": true,
        "acceptedSuggestion": false
      }
    }
  ],
  "totals": {
    "totalAmount": 312.0,
    "totalItems": 4,
    "brandedAmount": 312.0,
    "unbrandedAmount": 0.0,
    "brandedCount": 4,
    "unbrandedCount": 0,
    "uniqueBrandsCount": 2
  },
  "transactionContext": {
    "duration": 5.68,
    "paymentMethod": "cash",
    "timeOfDay": "unspecified",
    "dayType": "weekend",
    "audioTranscript": "cherry dalawa prepaid yung tatlo chips isa softdrinks lang",
    "processingMethods": [
      "stt_transcription",
      "brand_detection",
      "fuzzy_matching",
      "pricing_lookup",
      "totals_calculation",
      "confidence_scoring"
    ]
  },
  "privacy": {
    "audioStored": false,
    "brandAnalysisOnly": true,
    "noFacialRecognition": true,
    "noImageProcessing": true,
    "dataRetentionDays": 30,
    "anonymizationLevel": "high",
    "consentTimestamp": "2025-09-14T12:29:45.994936.000Z"
  },
  "processingTime": 10.39,
  "edgeVersion": "v2.0.0-stt-only"
}