{
  "storeId": "108",
  "deviceId": "SCOUTPI-0006",
  "timestamp": "",
  "transactionId": "4ddfdd67-ef48-4ddd-bc90-536ecc5d96b9",
  "brandDetection": {
    "detectedBrands": {
      "Regent": 0.83,
      "Magic": 0.83,
      "Piattos": 0.83
    },
    "explicitMentions": [
      {
        "brand": "Regent",
        "category": "Snacks & Confectionery",
        "subcategory": "unspecified",
        "confidence": 0.83,
        "detection_type": "exact_match",
        "context": "regent isang pack magic"
      },
      {
        "brand": "Magic",
        "category": "Other Essentials",
        "subcategory": "unspecified",
        "confidence": 0.83,
        "detection_type": "exact_match",
        "context": "regent isang pack magic chips, please piattos"
      },
      {
        "brand": "Piattos",
        "category": "Salty Snacks (Chichirya)",
        "subcategory": "unspecified",
        "confidence": 0.83,
        "detection_type": "exact_match",
        "context": "magic chips, please piattos dalawa lang"
      }
    ],
    "implicitSignals": [],
    "detectionMethods": [
      "exact_match"
    ],
    "categoryBrandMapping": {
      "Snacks & Confectionery": {
        "branded": [
          {
            "brand": "Regent",
            "confidence": 0.83,
            "quantity": 1
          }
        ],
        "unbranded_volume": 0
      },
      "Other Essentials": {
        "branded": [
          {
            "brand": "Magic",
            "confidence": 0.83,
            "quantity": 1
          }
        ],
        "unbranded_volume": 0
      },
      "Salty Snacks (Chichirya)": {
        "branded": [
          {
            "brand": "Piattos",
            "confidence": 0.83,
            "quantity": 2
          }
        ],
        "unbranded_volume": 0
      }
    }
  },
  "items": [
    {
      "brandName": "Regent",
      "productName": "Regent Sweet Corn",
      "genericName": "Product",
      "localName": "regent",
      "sku": "REGENT-SWEET-CORN-60G",
      "quantity": 1,
      "unit": "pc",
      "unitPrice": 16.0,
      "totalPrice": 16.0,
      "category": "Snacks & Confectionery",
      "isUnbranded": false,
      "isBulk": false,
      "detectionMethod": "stt_brand_only",
      "confidence": 0.83,
      "brandConfidence": 0.85,
      "suggestedBrands": null,
      "notes": "STT: 'regent isang pack magic'",
      "customerRequest": {
        "requestType": "branded",
        "specificBrand": true,
        "pointedToProduct": false,
        "acceptedSuggestion": false
      }
    },
    {
      "brandName": "Magic",
      "productName": "Magic Chips Barbecue Big Pack",
      "genericName": "Product",
      "localName": "chips",
      "sku": "MAGIC-CHIPS-BBQ-100G",
      "quantity": 1,
      "unit": "pc",
      "unitPrice": 25.45,
      "totalPrice": 25.45,
      "category": "Other Essentials",
      "isUnbranded": false,
      "isBulk": false,
      "detectionMethod": "stt_brand_only",
      "confidence": 0.83,
      "brandConfidence": 0.85,
      "suggestedBrands": null,
      "notes": "STT: 'regent isang pack magic chips, please piattos'",
      "customerRequest": {
        "requestType": "branded",
        "specificBrand": true,
        "pointedToProduct": false,
        "acceptedSuggestion": false
      }
    },
    {
      "brandName": "Piattos",
      "productName": "Piattos Cheese",
      "genericName": "Product",
      "localName": "chips",
      "sku": "PIATTOS-CHEESE-85G",
      "quantity": 2,
      "unit": "pc",
      "unitPrice": 35.95,
      "totalPrice": 71.9,
      "category": "Salty Snacks (Chichirya)",
      "isUnbranded": false,
      "isBulk": false,
      "detectionMethod": "stt_brand_only",
      "confidence": 0.83,
      "brandConfidence": 0.85,
      "suggestedBrands": null,
      "notes": "STT: 'magic chips, please piattos dalawa lang'",
      "customerRequest": {
        "requestType": "branded",
        "specificBrand": true,
        "pointedToProduct": false,
        "acceptedSuggestion": false
      }
    }
  ],
  "totals": {
    "totalAmount": 113.35,
    "totalItems": 4,
    "brandedAmount": 113.35,
    "unbrandedAmount": 0.0,
    "brandedCount": 4,
    "unbrandedCount": 0,
    "uniqueBrandsCount": 3
  },
  "transactionContext": {
    "duration": 2.0,
    "paymentMethod": "cash",
    "timeOfDay": "unspecified",
    "dayType": "weekend",
    "audioTranscript": "regent isang pack magic chips, please piattos dalawa lang",
    "processingMethods": [
      "stt_transcription",
      "brand_detection",
      "fuzzy_matching",
      "pricing_lookup",
      "totals_calculation",
      "confidence_scoring"
    ]
  },
  "privacy": {
    "audioStored": false,
    "brandAnalysisOnly": true,
    "noFacialRecognition": true,
    "noImageProcessing": true,
    "dataRetentionDays": 30,
    "anonymizationLevel": "high",
    "consentTimestamp": "2025-09-14T15:58:28.122262.000Z"
  },
  "processingTime": 13.52,
  "edgeVersion": "v2.0.0-stt-only"
}