{
  "storeId": "108",
  "deviceId": "SCOUTPI-0006",
  "timestamp": "",
  "transactionId": "5a391e6b-9318-4543-98aa-25663633fd6a",
  "brandDetection": {
    "detectedBrands": {
      "Coca-Cola": 0.274,
      "Extra Joss": 0.83
    },
    "explicitMentions": [
      {
        "brand": "Coca-Cola",
        "category": "Non-Alcoholic",
        "subcategory": "carbonated_soft_drink",
        "confidence": 0.274,
        "detection_type": "exact_match",
        "context": "coca cola isa extra joss dalawa yung malaki coca c..."
      },
      {
        "brand": "Extra Joss",
        "category": "Other Essentials",
        "subcategory": "unspecified",
        "confidence": 0.83,
        "detection_type": "exact_match",
        "context": "coca cola isa extra joss dalawa yung malaki coca c..."
      }
    ],
    "implicitSignals": [],
    "detectionMethods": [
      "exact_match"
    ],
    "categoryBrandMapping": {
      "Non-Alcoholic": {
        "branded": [
          {
            "brand": "Coca-Cola",
            "confidence": 0.274,
            "quantity": 3
          }
        ],
        "unbranded_volume": 0
      },
      "Other Essentials": {
        "branded": [
          {
            "brand": "Extra Joss",
            "confidence": 0.83,
            "quantity": 2
          }
        ],
        "unbranded_volume": 0
      }
    }
  },
  "items": [
    {
      "brandName": "Coca-Cola",
      "productName": "Coca-Cola Regular 1.5L",
      "genericName": "Product",
      "localName": "coke",
      "sku": "COKE-REG-1.5L",
      "quantity": 3,
      "unit": "pc",
      "unitPrice": 88.0,
      "totalPrice": 264.0,
      "category": "Non-Alcoholic",
      "isUnbranded": false,
      "isBulk": false,
      "detectionMethod": "stt_brand_only",
      "confidence": 0.274,
      "brandConfidence": 0.482,
      "suggestedBrands": null,
      "notes": "STT: 'coca cola isa extra joss dalawa yung malaki coca c...'",
      "customerRequest": {
        "requestType": "branded",
        "specificBrand": true,
        "pointedToProduct": true,
        "acceptedSuggestion": false
      }
    },
    {
      "brandName": "Extra Joss",
      "productName": "Extra Joss Energy Drink",
      "genericName": "Product",
      "localName": "extra",
      "sku": "EXTRA-JOSS-4G",
      "quantity": 2,
      "unit": "sachet",
      "unitPrice": 7.0,
      "totalPrice": 14.0,
      "category": "Other Essentials",
      "isUnbranded": false,
      "isBulk": false,
      "detectionMethod": "stt_brand_only",
      "confidence": 0.83,
      "brandConfidence": 0.85,
      "suggestedBrands": null,
      "notes": "STT: 'coca cola isa extra joss dalawa yung malaki coca c...'",
      "customerRequest": {
        "requestType": "branded",
        "specificBrand": true,
        "pointedToProduct": true,
        "acceptedSuggestion": false
      }
    }
  ],
  "totals": {
    "totalAmount": 278.0,
    "totalItems": 5,
    "brandedAmount": 278.0,
    "unbrandedAmount": 0.0,
    "brandedCount": 5,
    "unbrandedCount": 0,
    "uniqueBrandsCount": 2
  },
  "transactionContext": {
    "duration": 5.8,
    "paymentMethod": "cash",
    "timeOfDay": "unspecified",
    "dayType": "weekend",
    "audioTranscript": "coca cola isa extra joss dalawa yung malaki coca cola",
    "processingMethods": [
      "stt_transcription",
      "brand_detection",
      "fuzzy_matching",
      "pricing_lookup",
      "totals_calculation",
      "confidence_scoring"
    ]
  },
  "privacy": {
    "audioStored": false,
    "brandAnalysisOnly": true,
    "noFacialRecognition": true,
    "noImageProcessing": true,
    "dataRetentionDays": 30,
    "anonymizationLevel": "high",
    "consentTimestamp": "2025-09-14T16:20:05.253344.000Z"
  },
  "processingTime": 9.91,
  "edgeVersion": "v2.0.0-stt-only"
}