{
  "storeId": "108",
  "deviceId": "SCOUTPI-0006",
  "timestamp": "",
  "transactionId": "9ac02c03-de88-462e-864b-a0a8039a93c7",
  "brandDetection": {
    "detectedBrands": {
      "Dewberry": 0.83,
      "Hello": 0.83,
      "Voice": 0.83
    },
    "explicitMentions": [
      {
        "brand": "Dewberry",
        "category": "Other Essentials",
        "subcategory": "unspecified",
        "confidence": 0.83,
        "detection_type": "exact_match",
        "context": "isa Dewberry tatlo Hello Voice,"
      },
      {
        "brand": "Hello",
        "category": "unspecified",
        "subcategory": "unspecified",
        "confidence": 0.83,
        "detection_type": "exact_match",
        "context": "isa Dewberry tatlo Hello Voice, pabili"
      },
      {
        "brand": "Voice",
        "category": "Other Essentials",
        "subcategory": "unspecified",
        "confidence": 0.83,
        "detection_type": "exact_match",
        "context": "Dewberry tatlo Hello Voice, pabili"
      }
    ],
    "implicitSignals": [],
    "detectionMethods": [
      "exact_match"
    ],
    "categoryBrandMapping": {
      "Other Essentials": {
        "branded": [
          {
            "brand": "Dewberry",
            "confidence": 0.83,
            "quantity": 1
          },
          {
            "brand": "Voice",
            "confidence": 0.83,
            "quantity": 1
          }
        ],
        "unbranded_volume": 0
      },
      "unspecified": {
        "branded": [
          {
            "brand": "Hello",
            "confidence": 0.83,
            "quantity": 3
          }
        ],
        "unbranded_volume": 0
      }
    }
  },
  "items": [
    {
      "brandName": "Dewberry",
      "productName": "Dewberry Blueberry",
      "genericName": "Product",
      "localName": "dewberry",
      "sku": "DEWBERRY-BLUEBERRY-33G",
      "quantity": 1,
      "unit": "pc",
      "unitPrice": 8.0,
      "totalPrice": 8.0,
      "category": "Other Essentials",
      "isUnbranded": false,
      "isBulk": false,
      "detectionMethod": "stt_brand_only",
      "confidence": 0.83,
      "brandConfidence": 0.88,
      "suggestedBrands": null,
      "notes": "STT: 'isa Dewberry tatlo Hello Voice,'",
      "customerRequest": {
        "requestType": "branded",
        "specificBrand": true,
        "pointedToProduct": false,
        "acceptedSuggestion": false
      }
    },
    {
      "brandName": "Hello",
      "productName": "Hello Chocolate",
      "genericName": "Product",
      "localName": "coke",
      "sku": "HELLO-CHOCOLATE-38G",
      "quantity": 3,
      "unit": "pc",
      "unitPrice": 8.0,
      "totalPrice": 24.0,
      "category": "Other Essentials",
      "isUnbranded": false,
      "isBulk": false,
      "detectionMethod": "stt_brand_only",
      "confidence": 0.83,
      "brandConfidence": 0.88,
      "suggestedBrands": null,
      "notes": "STT: 'isa Dewberry tatlo Hello Voice, pabili'",
      "customerRequest": {
        "requestType": "branded",
        "specificBrand": true,
        "pointedToProduct": false,
        "acceptedSuggestion": false
      }
    },
    {
      "brandName": "Voice",
      "productName": "Voice Combo Sandwich",
      "genericName": "Product",
      "localName": "voice",
      "sku": "VOICE-COMBO-35G",
      "quantity": 1,
      "unit": "pc",
      "unitPrice": 8.0,
      "totalPrice": 8.0,
      "category": "Other Essentials",
      "isUnbranded": false,
      "isBulk": false,
      "detectionMethod": "stt_brand_only",
      "confidence": 0.83,
      "brandConfidence": 0.88,
      "suggestedBrands": null,
      "notes": "STT: 'Dewberry tatlo Hello Voice, pabili'",
      "customerRequest": {
        "requestType": "branded",
        "specificBrand": true,
        "pointedToProduct": false,
        "acceptedSuggestion": false
      }
    }
  ],
  "totals": {
    "totalAmount": 40.0,
    "totalItems": 5,
    "brandedAmount": 40.0,
    "unbrandedAmount": 0.0,
    "brandedCount": 5,
    "unbrandedCount": 0,
    "uniqueBrandsCount": 3
  },
  "transactionContext": {
    "duration": 1.0,
    "paymentMethod": "cash",
    "timeOfDay": "unspecified",
    "dayType": "weekend",
    "audioTranscript": "isa Dewberry tatlo Hello Voice, pabili",
    "processingMethods": [
      "stt_transcription",
      "brand_detection",
      "fuzzy_matching",
      "pricing_lookup",
      "totals_calculation",
      "confidence_scoring"
    ]
  },
  "privacy": {
    "audioStored": false,
    "brandAnalysisOnly": true,
    "noFacialRecognition": true,
    "noImageProcessing": true,
    "dataRetentionDays": 30,
    "anonymizationLevel": "high",
    "consentTimestamp": "2025-09-14T11:47:59.055813.000Z"
  },
  "processingTime": 13.6,
  "edgeVersion": "v2.0.0-stt-only"
}