{
  "storeId": "108",
  "deviceId": "SCOUTPI-0006",
  "timestamp": "",
  "transactionId": "dfc9d588-b46c-4c19-8afc-8a22dc3051d4",
  "brandDetection": {
    "detectedBrands": {
      "C2": 0.83
    },
    "explicitMentions": [
      {
        "brand": "C2",
        "category": "unspecified",
        "subcategory": "unspecified",
        "confidence": 0.83,
        "detection_type": "exact_match",
        "context": "c2 tatlong piraso tubig"
      }
    ],
    "implicitSignals": [],
    "detectionMethods": [
      "exact_match"
    ],
    "categoryBrandMapping": {
      "unspecified": {
        "branded": [
          {
            "brand": "C2",
            "confidence": 0.83,
            "quantity": 3
          }
        ],
        "unbranded_volume": 0
      }
    }
  },
  "items": [
    {
      "brandName": "C2",
      "productName": "C2 Green Tea Apple 500ml",
      "genericName": "Product",
      "localName": "tubig",
      "sku": "C2-APPLE-500ML",
      "quantity": 3,
      "unit": "pc",
      "unitPrice": 33.0,
      "totalPrice": 99.0,
      "category": "unspecified",
      "isUnbranded": false,
      "isBulk": false,
      "detectionMethod": "stt_brand_only",
      "confidence": 0.83,
      "brandConfidence": 0.85,
      "suggestedBrands": null,
      "notes": "STT: 'c2 tatlong piraso tubig'",
      "customerRequest": {
        "requestType": "branded",
        "specificBrand": true,
        "pointedToProduct": false,
        "acceptedSuggestion": false
      }
    }
  ],
  "totals": {
    "totalAmount": 99.0,
    "totalItems": 3,
    "brandedAmount": 99.0,
    "unbrandedAmount": 0.0,
    "brandedCount": 3,
    "unbrandedCount": 0,
    "uniqueBrandsCount": 1
  },
  "transactionContext": {
    "duration": 5.76,
    "paymentMethod": "cash",
    "timeOfDay": "unspecified",
    "dayType": "weekend",
    "audioTranscript": "c2 tatlong piraso tubig",
    "processingMethods": [
      "stt_transcription",
      "brand_detection",
      "fuzzy_matching",
      "pricing_lookup",
      "totals_calculation",
      "confidence_scoring"
    ]
  },
  "privacy": {
    "audioStored": false,
    "brandAnalysisOnly": true,
    "noFacialRecognition": true,
    "noImageProcessing": true,
    "dataRetentionDays": 30,
    "anonymizationLevel": "high",
    "consentTimestamp": "2025-09-14T14:23:59.078578.000Z"
  },
  "processingTime": 5.51,
  "edgeVersion": "v2.0.0-stt-only"
}