{
  "storeId": "109",
  "deviceId": "SCOUTPI-0009",
  "timestamp": "",
  "transactionId": "652be738-3792-4b78-999c-50314185b6d3",
  "brandDetection": {
    "detectedBrands": {
      "Datu Puti": 0.83,
      "Camel": 0.83
    },
    "explicitMentions": [
      {
        "brand": "Datu Puti",
        "category": "Cooking Essentials",
        "subcategory": "unspecified",
        "confidence": 0.83,
        "detection_type": "exact_match",
        "context": "Datu Puti dalawa Camel isa lang meron pang Datu Pu..."
      },
      {
        "brand": "Camel",
        "category": "Tobacco Products",
        "subcategory": "unspecified",
        "confidence": 0.83,
        "detection_type": "exact_match",
        "context": "Datu Puti dalawa Camel isa lang meron"
      }
    ],
    "implicitSignals": [],
    "detectionMethods": [
      "exact_match"
    ],
    "categoryBrandMapping": {
      "Cooking Essentials": {
        "branded": [
          {
            "brand": "Datu Puti",
            "confidence": 0.83,
            "quantity": 3
          }
        ],
        "unbranded_volume": 0
      },
      "Tobacco Products": {
        "branded": [
          {
            "brand": "Camel",
            "confidence": 0.83,
            "quantity": 1
          }
        ],
        "unbranded_volume": 0
      }
    }
  },
  "items": [
    {
      "brandName": "Datu Puti",
      "productName": "Datu Puti Vinegar Large",
      "genericName": "Product",
      "localName": "datu",
      "sku": "DATU-PUTI-VINEGAR-1L",
      "quantity": 3,
      "unit": "pc",
      "unitPrice": 35.0,
      "totalPrice": 105.0,
      "category": "Cooking Essentials",
      "isUnbranded": false,
      "isBulk": false,
      "detectionMethod": "stt_brand_only",
      "confidence": 0.83,
      "brandConfidence": 0.79,
      "suggestedBrands": null,
      "notes": "STT: 'Datu Puti dalawa Camel isa lang meron pang Datu Pu...'",
      "customerRequest": {
        "requestType": "branded",
        "specificBrand": true,
        "pointedToProduct": false,
        "acceptedSuggestion": false
      }
    },
    {
      "brandName": "Camel",
      "productName": "Camel Activate Purple 20s",
      "genericName": "Product",
      "localName": "camel",
      "sku": "CAMEL-ACTIVATE-PURPLE-20S-20 STICKS",
      "quantity": 1,
      "unit": "pc",
      "unitPrice": 176.0,
      "totalPrice": 176.0,
      "category": "Tobacco Products",
      "isUnbranded": false,
      "isBulk": false,
      "detectionMethod": "stt_brand_only",
      "confidence": 0.83,
      "brandConfidence": 0.85,
      "suggestedBrands": null,
      "notes": "STT: 'Datu Puti dalawa Camel isa lang meron'",
      "customerRequest": {
        "requestType": "branded",
        "specificBrand": true,
        "pointedToProduct": false,
        "acceptedSuggestion": false
      }
    }
  ],
  "totals": {
    "totalAmount": 281.0,
    "totalItems": 4,
    "brandedAmount": 281.0,
    "unbrandedAmount": 0.0,
    "brandedCount": 4,
    "unbrandedCount": 0,
    "uniqueBrandsCount": 2
  },
  "transactionContext": {
    "duration": 5.8,
    "paymentMethod": "cash",
    "timeOfDay": "unspecified",
    "dayType": "weekend",
    "audioTranscript": "Datu Puti dalawa Camel isa lang meron pang Datu Puti",
    "processingMethods": [
      "stt_transcription",
      "brand_detection",
      "fuzzy_matching",
      "pricing_lookup",
      "totals_calculation",
      "confidence_scoring"
    ]
  },
  "privacy": {
    "audioStored": false,
    "brandAnalysisOnly": true,
    "noFacialRecognition": true,
    "noImageProcessing": true,
    "dataRetentionDays": 30,
    "anonymizationLevel": "high",
    "consentTimestamp": "2025-09-14T03:23:36.482649.000Z"
  },
  "processingTime": 9.62,
  "edgeVersion": "v2.0.0-stt-only"
}