{
  "storeId": "109",
  "deviceId": "SCOUTPI-0009",
  "timestamp": "",
  "transactionId": "eced3c39-b754-478e-acd5-f158b7ff247d",
  "brandDetection": {
    "detectedBrands": {
      "Great Taste": 0.83,
      "Coca-Cola": 0.212,
      "Milo": 0.83
    },
    "explicitMentions": [
      {
        "brand": "Great Taste",
        "category": "Beverages",
        "subcategory": "unspecified",
        "confidence": 0.83,
        "detection_type": "exact_match",
        "context": "great taste po isang coke lang pabili ng milo"
      },
      {
        "brand": "Coca-Cola",
        "category": "Non-Alcoholic",
        "subcategory": "carbonated_soft_drink",
        "confidence": 0.212,
        "detection_type": "exact_match",
        "context": "great taste po isang coke lang pabili ng milo"
      },
      {
        "brand": "Milo",
        "category": "unspecified",
        "subcategory": "unspecified",
        "confidence": 0.83,
        "detection_type": "exact_match",
        "context": "lang pabili ng milo"
      }
    ],
    "implicitSignals": [],
    "detectionMethods": [
      "exact_match"
    ],
    "categoryBrandMapping": {
      "Beverages": {
        "branded": [
          {
            "brand": "Great Taste",
            "confidence": 0.83,
            "quantity": 1
          }
        ],
        "unbranded_volume": 0
      },
      "Non-Alcoholic": {
        "branded": [
          {
            "brand": "Coca-Cola",
            "confidence": 0.212,
            "quantity": 1
          }
        ],
        "unbranded_volume": 0
      },
      "unspecified": {
        "branded": [
          {
            "brand": "Milo",
            "confidence": 0.83,
            "quantity": 1
          }
        ],
        "unbranded_volume": 0
      }
    }
  },
  "items": [
    {
      "brandName": "Great Taste",
      "productName": "Great Taste Premium Blend",
      "genericName": "Product",
      "localName": "coke",
      "sku": "GREAT-TASTE-PREMIUM-25G",
      "quantity": 1,
      "unit": "sachet",
      "unitPrice": 21.0,
      "totalPrice": 21.0,
      "category": "Beverages",
      "isUnbranded": false,
      "isBulk": false,
      "detectionMethod": "stt_brand_only",
      "confidence": 0.83,
      "brandConfidence": 0.88,
      "suggestedBrands": null,
      "notes": "STT: 'great taste po isang coke lang pabili ng milo'",
      "customerRequest": {
        "requestType": "branded",
        "specificBrand": true,
        "pointedToProduct": false,
        "acceptedSuggestion": false
      }
    },
    {
      "brandName": "Coca-Cola",
      "productName": "Coca-Cola 355ml Can",
      "genericName": "Product",
      "localName": "coke",
      "sku": "COKE-355ML",
      "quantity": 1,
      "unit": "pc",
      "unitPrice": 28.0,
      "totalPrice": 28.0,
      "category": "Non-Alcoholic",
      "isUnbranded": false,
      "isBulk": false,
      "detectionMethod": "stt_brand_only",
      "confidence": 0.212,
      "brandConfidence": 0.541,
      "suggestedBrands": null,
      "notes": "STT: 'great taste po isang coke lang pabili ng milo'",
      "customerRequest": {
        "requestType": "branded",
        "specificBrand": true,
        "pointedToProduct": false,
        "acceptedSuggestion": false
      }
    },
    {
      "brandName": "Milo",
      "productName": "Milo Chocolate Drink Pack",
      "genericName": "Product",
      "localName": "coke",
      "sku": "MILO-150G",
      "quantity": 1,
      "unit": "pc",
      "unitPrice": 65.0,
      "totalPrice": 65.0,
      "category": "Pantry Staples & Groceries",
      "isUnbranded": false,
      "isBulk": false,
      "detectionMethod": "stt_brand_only",
      "confidence": 0.83,
      "brandConfidence": 0.88,
      "suggestedBrands": null,
      "notes": "STT: 'lang pabili ng milo'",
      "customerRequest": {
        "requestType": "branded",
        "specificBrand": true,
        "pointedToProduct": false,
        "acceptedSuggestion": false
      }
    }
  ],
  "totals": {
    "totalAmount": 114.0,
    "totalItems": 3,
    "brandedAmount": 114.0,
    "unbrandedAmount": 0.0,
    "brandedCount": 3,
    "unbrandedCount": 0,
    "uniqueBrandsCount": 3
  },
  "transactionContext": {
    "duration": 5.7,
    "paymentMethod": "cash",
    "timeOfDay": "unspecified",
    "dayType": "weekend",
    "audioTranscript": "great taste po isang coke lang pabili ng milo",
    "processingMethods": [
      "stt_transcription",
      "brand_detection",
      "fuzzy_matching",
      "pricing_lookup",
      "totals_calculation",
      "confidence_scoring"
    ]
  },
  "privacy": {
    "audioStored": false,
    "brandAnalysisOnly": true,
    "noFacialRecognition": true,
    "noImageProcessing": true,
    "dataRetentionDays": 30,
    "anonymizationLevel": "high",
    "consentTimestamp": "2025-09-14T06:18:32.671325.000Z"
  },
  "processingTime": 14.55,
  "edgeVersion": "v2.0.0-stt-only"
}