{
  "storeId": "110",
  "deviceId": "SCOUTPI-0010",
  "timestamp": "",
  "transactionId": "6ea28f91-fd12-4742-a960-13b26e3bdc96",
  "brandDetection": {
    "detectedBrands": {
      "Maggi": 0.83
    },
    "explicitMentions": [
      {
        "brand": "Maggi",
        "category": "Instant Foods",
        "subcategory": "unspecified",
        "confidence": 0.83,
        "detection_type": "exact_match",
        "context": "maggi po dalawang maggi"
      }
    ],
    "implicitSignals": [],
    "detectionMethods": [
      "exact_match"
    ],
    "categoryBrandMapping": {
      "Instant Foods": {
        "branded": [
          {
            "brand": "Maggi",
            "confidence": 0.83,
            "quantity": 2
          }
        ],
        "unbranded_volume": 0
      }
    }
  },
  "items": [
    {
      "brandName": "Maggi",
      "productName": "Maggi Magic Sarap Pack",
      "genericName": "Product",
      "localName": "noodles",
      "sku": "MAGGI-SARAP-50G",
      "quantity": 2,
      "unit": "pc",
      "unitPrice": 18.0,
      "totalPrice": 36.0,
      "category": "Instant Foods",
      "isUnbranded": false,
      "isBulk": false,
      "detectionMethod": "stt_brand_only",
      "confidence": 0.83,
      "brandConfidence": 0.85,
      "suggestedBrands": null,
      "notes": "STT: 'maggi po dalawang maggi'",
      "customerRequest": {
        "requestType": "branded",
        "specificBrand": true,
        "pointedToProduct": false,
        "acceptedSuggestion": false
      }
    }
  ],
  "totals": {
    "totalAmount": 36.0,
    "totalItems": 2,
    "brandedAmount": 36.0,
    "unbrandedAmount": 0.0,
    "brandedCount": 2,
    "unbrandedCount": 0,
    "uniqueBrandsCount": 1
  },
  "transactionContext": {
    "duration": 1.0,
    "paymentMethod": "cash",
    "timeOfDay": "unspecified",
    "dayType": "weekday",
    "audioTranscript": "maggi po dalawang maggi meron ka bang maggi?",
    "processingMethods": [
      "stt_transcription",
      "brand_detection",
      "fuzzy_matching",
      "pricing_lookup",
      "totals_calculation",
      "confidence_scoring"
    ]
  },
  "privacy": {
    "audioStored": false,
    "brandAnalysisOnly": true,
    "noFacialRecognition": true,
    "noImageProcessing": true,
    "dataRetentionDays": 30,
    "anonymizationLevel": "high",
    "consentTimestamp": "2025-09-12T03:42:38.638509.000Z"
  },
  "processingTime": 5.48,
  "edgeVersion": "v2.0.0-stt-only"
}