{
  "storeId": "110",
  "deviceId": "SCOUTPI-0010",
  "timestamp": "",
  "transactionId": "6f42455f-02aa-44d8-a8a6-dd37167863fb",
  "brandDetection": {
    "detectedBrands": {
      "Coca-Cola": 0.244,
      "Datu Puti": 0.8,
      "Alaska": 0.8
    },
    "explicitMentions": [
      {
        "brand": "Coca-Cola",
        "category": "Non-Alcoholic",
        "subcategory": "carbonated_soft_drink",
        "confidence": 0.244,
        "detection_type": "exact_match",
        "context": "Coca Cola? Datu Puti, meron? Alaska gatas?"
      },
      {
        "brand": "Datu Puti",
        "category": "Cooking Essentials",
        "subcategory": "unspecified",
        "confidence": 0.8,
        "detection_type": "exact_match",
        "context": "Coca Cola? Datu Puti, meron? Alaska gatas?"
      },
      {
        "brand": "Alaska",
        "category": "unspecified",
        "subcategory": "unspecified",
        "confidence": 0.8,
        "detection_type": "exact_match",
        "context": "Datu Puti, meron? Alaska gatas?"
      }
    ],
    "implicitSignals": [],
    "detectionMethods": [
      "exact_match"
    ],
    "categoryBrandMapping": {
      "Non-Alcoholic": {
        "branded": [
          {
            "brand": "Coca-Cola",
            "confidence": 0.244,
            "quantity": 1
          }
        ],
        "unbranded_volume": 0
      },
      "Cooking Essentials": {
        "branded": [
          {
            "brand": "Datu Puti",
            "confidence": 0.8,
            "quantity": 1
          }
        ],
        "unbranded_volume": 0
      },
      "unspecified": {
        "branded": [
          {
            "brand": "Alaska",
            "confidence": 0.8,
            "quantity": 1
          }
        ],
        "unbranded_volume": 0
      }
    }
  },
  "items": [
    {
      "brandName": "Coca-Cola",
      "productName": "Coca-Cola 355ml Can",
      "genericName": "Product",
      "localName": "gatas",
      "sku": "COKE-355ML",
      "quantity": 1,
      "unit": "pc",
      "unitPrice": 28.0,
      "totalPrice": 28.0,
      "category": "Non-Alcoholic",
      "isUnbranded": false,
      "isBulk": false,
      "detectionMethod": "stt_brand_only",
      "confidence": 0.244,
      "brandConfidence": 0.487,
      "suggestedBrands": null,
      "notes": "STT: 'Coca Cola? Datu Puti, meron? Alaska gatas?'",
      "customerRequest": {
        "requestType": "branded",
        "specificBrand": true,
        "pointedToProduct": false,
        "acceptedSuggestion": false
      }
    },
    {
      "brandName": "Datu Puti",
      "productName": "Datu Puti Vinegar Large",
      "genericName": "Product",
      "localName": "gatas",
      "sku": "DATU-PUTI-VINEGAR-1L",
      "quantity": 1,
      "unit": "pc",
      "unitPrice": 35.0,
      "totalPrice": 35.0,
      "category": "Cooking Essentials",
      "isUnbranded": false,
      "isBulk": false,
      "detectionMethod": "stt_brand_only",
      "confidence": 0.8,
      "brandConfidence": 0.795,
      "suggestedBrands": null,
      "notes": "STT: 'Coca Cola? Datu Puti, meron? Alaska gatas?'",
      "customerRequest": {
        "requestType": "branded",
        "specificBrand": true,
        "pointedToProduct": false,
        "acceptedSuggestion": false
      }
    },
    {
      "brandName": "Alaska",
      "productName": "Alaska Condensada",
      "genericName": "Product",
      "localName": "gatas",
      "sku": "ALASKA-CONDENSED-300ML",
      "quantity": 1,
      "unit": "pc",
      "unitPrice": 35.0,
      "totalPrice": 35.0,
      "category": "unspecified",
      "isUnbranded": false,
      "isBulk": false,
      "detectionMethod": "stt_brand_only",
      "confidence": 0.8,
      "brandConfidence": 0.795,
      "suggestedBrands": null,
      "notes": "STT: 'Datu Puti, meron? Alaska gatas?'",
      "customerRequest": {
        "requestType": "branded",
        "specificBrand": true,
        "pointedToProduct": false,
        "acceptedSuggestion": false
      }
    }
  ],
  "totals": {
    "totalAmount": 98.0,
    "totalItems": 3,
    "brandedAmount": 98.0,
    "unbrandedAmount": 0.0,
    "brandedCount": 3,
    "unbrandedCount": 0,
    "uniqueBrandsCount": 3
  },
  "transactionContext": {
    "duration": 5.84,
    "paymentMethod": "cash",
    "timeOfDay": "unspecified",
    "dayType": "weekday",
    "audioTranscript": "Coca Cola? Datu Puti, meron? Alaska gatas?",
    "processingMethods": [
      "stt_transcription",
      "brand_detection",
      "fuzzy_matching",
      "pricing_lookup",
      "totals_calculation",
      "confidence_scoring"
    ]
  },
  "privacy": {
    "audioStored": false,
    "brandAnalysisOnly": true,
    "noFacialRecognition": true,
    "noImageProcessing": true,
    "dataRetentionDays": 30,
    "anonymizationLevel": "high",
    "consentTimestamp": "2025-09-12T05:14:45.870688.000Z"
  },
  "processingTime": 15.84,
  "edgeVersion": "v2.0.0-stt-only"
}