{
  "storeId": "103",
  "deviceId": "SCOUTPI-0003",
  "timestamp": "",
  "transactionId": "d64564d8-ce8f-413b-b384-c0cd04945425",
  "brandDetection": {
    "detectedBrands": {
      "Datu Puti": 0.77
    },
    "explicitMentions": [
      {
        "brand": "Datu Puti",
        "category": "Cooking Essentials",
        "subcategory": "unspecified",
        "confidence": 0.77,
        "detection_type": "exact_match",
        "context": "1  \n00:00:00,000 --> 00:00:02,420  \n Datu Puti'y a..."
      }
    ],
    "implicitSignals": [],
    "detectionMethods": [
      "exact_match"
    ],
    "categoryBrandMapping": {
      "Cooking Essentials": {
        "branded": [
          {
            "brand": "Datu Puti",
            "confidence": 0.77,
            "quantity": 1
          }
        ],
        "unbranded_volume": 0
      }
    }
  },
  "items": [
    {
      "brandName": "Datu Puti",
      "productName": "Datu Puti Vinegar Large",
      "genericName": "Product",
      "localName": "datu",
      "sku": "DATU-PUTI-VINEGAR-1L",
      "quantity": 1,
      "unit": "pc",
      "unitPrice": 35.0,
      "totalPrice": 35.0,
      "category": "Cooking Essentials",
      "isUnbranded": false,
      "isBulk": false,
      "detectionMethod": "stt_brand_only",
      "confidence": 0.77,
      "brandConfidence": 0.82,
      "suggestedBrands": null,
      "notes": "STT: '1  \n00:00:00,000 --> 00:00:02,420  \n Datu Puti'y a...'",
      "customerRequest": {
        "requestType": "branded",
        "specificBrand": true,
        "pointedToProduct": false,
        "acceptedSuggestion": false
      }
    }
  ],
  "totals": {
    "totalAmount": 35.0,
    "totalItems": 1,
    "brandedAmount": 35.0,
    "unbrandedAmount": 0.0,
    "brandedCount": 1,
    "unbrandedCount": 0,
    "uniqueBrandsCount": 1
  },
  "transactionContext": {
    "duration": 5.66,
    "paymentMethod": "cash",
    "timeOfDay": "unspecified",
    "dayType": "weekend",
    "audioTranscript": "1  \n00:00:00,000 --> 00:00:02,420  \n Datu Puti'y ang pwede mo, magandangin lang ang mula.  \n\n2  \n00:00:02,420 --> 00:00:05,160  \n Nagkakapisan na ang mula!  \n\n3  \n00:00:05,160 --> 00:00:05,660  \n NGAY!  ",
    "processingMethods": [
      "stt_transcription",
      "brand_detection",
      "fuzzy_matching",
      "pricing_lookup",
      "totals_calculation",
      "confidence_scoring"
    ]
  },
  "privacy": {
    "audioStored": false,
    "brandAnalysisOnly": true,
    "noFacialRecognition": true,
    "noImageProcessing": true,
    "dataRetentionDays": 30,
    "anonymizationLevel": "high",
    "consentTimestamp": "2025-09-13T21:06:53.420016.000Z"
  },
  "processingTime": 6.1,
  "edgeVersion": "v2.0.0-stt-only"
}