{
  "storeId": "103",
  "deviceId": "SCOUTPI-0003",
  "timestamp": "",
  "transactionId": "d6a75727-7f71-4121-95a5-a5886fbe2e1e",
  "brandDetection": {
    "detectedBrands": {
      "Gatorade": 0.77,
      "Coca-Cola": 0.214,
      "C2": 0.77
    },
    "explicitMentions": [
      {
        "brand": "Gatorade",
        "category": "Beverages",
        "subcategory": "unspecified",
        "confidence": 0.77,
        "detection_type": "exact_match",
        "context": "gatorade malamig coca cola"
      },
      {
        "brand": "Coca-Cola",
        "category": "Non-Alcoholic",
        "subcategory": "carbonated_soft_drink",
        "confidence": 0.214,
        "detection_type": "exact_match",
        "context": "gatorade malamig coca cola isa c2 dalawa po"
      },
      {
        "brand": "C2",
        "category": "unspecified",
        "subcategory": "unspecified",
        "confidence": 0.77,
        "detection_type": "exact_match",
        "context": "coca cola isa c2 dalawa po"
      }
    ],
    "implicitSignals": [],
    "detectionMethods": [
      "exact_match"
    ],
    "categoryBrandMapping": {
      "Beverages": {
        "branded": [
          {
            "brand": "Gatorade",
            "confidence": 0.77,
            "quantity": 1
          }
        ],
        "unbranded_volume": 0
      },
      "Non-Alcoholic": {
        "branded": [
          {
            "brand": "Coca-Cola",
            "confidence": 0.214,
            "quantity": 1
          }
        ],
        "unbranded_volume": 0
      },
      "unspecified": {
        "branded": [
          {
            "brand": "C2",
            "confidence": 0.77,
            "quantity": 3
          }
        ],
        "unbranded_volume": 0
      }
    }
  },
  "items": [
    {
      "brandName": "Gatorade",
      "productName": "Gatorade Blue Bolt",
      "genericName": "Product",
      "localName": "gatorade",
      "sku": "GATORADE-BLUE-500ML",
      "quantity": 1,
      "unit": "pc",
      "unitPrice": 45.0,
      "totalPrice": 45.0,
      "category": "unspecified",
      "isUnbranded": false,
      "isBulk": false,
      "detectionMethod": "stt_brand_only",
      "confidence": 0.77,
      "brandConfidence": 0.82,
      "suggestedBrands": null,
      "notes": "STT: 'gatorade malamig coca cola'",
      "customerRequest": {
        "requestType": "branded",
        "specificBrand": true,
        "pointedToProduct": false,
        "acceptedSuggestion": false
      }
    },
    {
      "brandName": "Coca-Cola",
      "productName": "Coca-Cola 355ml Can",
      "genericName": "Product",
      "localName": "coke",
      "sku": "COKE-355ML",
      "quantity": 1,
      "unit": "pc",
      "unitPrice": 28.0,
      "totalPrice": 28.0,
      "category": "Non-Alcoholic",
      "isUnbranded": false,
      "isBulk": false,
      "detectionMethod": "stt_brand_only",
      "confidence": 0.214,
      "brandConfidence": 0.512,
      "suggestedBrands": null,
      "notes": "STT: 'gatorade malamig coca cola isa c2 dalawa po'",
      "customerRequest": {
        "requestType": "branded",
        "specificBrand": true,
        "pointedToProduct": false,
        "acceptedSuggestion": false
      }
    },
    {
      "brandName": "C2",
      "productName": "C2 Green Tea Apple 500ml",
      "genericName": "Product",
      "localName": "c2",
      "sku": "C2-APPLE-500ML",
      "quantity": 3,
      "unit": "pc",
      "unitPrice": 33.0,
      "totalPrice": 99.0,
      "category": "unspecified",
      "isUnbranded": false,
      "isBulk": false,
      "detectionMethod": "stt_brand_only",
      "confidence": 0.77,
      "brandConfidence": 0.76,
      "suggestedBrands": null,
      "notes": "STT: 'coca cola isa c2 dalawa po'",
      "customerRequest": {
        "requestType": "branded",
        "specificBrand": true,
        "pointedToProduct": false,
        "acceptedSuggestion": false
      }
    }
  ],
  "totals": {
    "totalAmount": 172.0,
    "totalItems": 5,
    "brandedAmount": 172.0,
    "unbrandedAmount": 0.0,
    "brandedCount": 5,
    "unbrandedCount": 0,
    "uniqueBrandsCount": 3
  },
  "transactionContext": {
    "duration": 5.72,
    "paymentMethod": "cash",
    "timeOfDay": "unspecified",
    "dayType": "weekend",
    "audioTranscript": "gatorade malamig coca cola isa c2 dalawa po",
    "processingMethods": [
      "stt_transcription",
      "brand_detection",
      "fuzzy_matching",
      "pricing_lookup",
      "totals_calculation",
      "confidence_scoring"
    ]
  },
  "privacy": {
    "audioStored": false,
    "brandAnalysisOnly": true,
    "noFacialRecognition": true,
    "noImageProcessing": true,
    "dataRetentionDays": 30,
    "anonymizationLevel": "high",
    "consentTimestamp": "2025-09-13T14:16:09.882129.000Z"
  },
  "processingTime": 18.41,
  "edgeVersion": "v2.0.0-stt-only"
}