{
  "storeId": "103",
  "deviceId": "SCOUTPI-0003",
  "timestamp": "",
  "transactionId": "f608e7d6-55aa-42f2-8938-a0af0232ce34",
  "brandDetection": {
    "detectedBrands": {
      "Surf": 0.83,
      "Coca-Cola": 0.274,
      "TNT": 0.83
    },
    "explicitMentions": [
      {
        "brand": "Surf",
        "category": "Laundry",
        "subcategory": "unspecified",
        "confidence": 0.83,
        "detection_type": "exact_match",
        "context": "TNT dalawa Surf isang pack Coca"
      },
      {
        "brand": "Coca-Cola",
        "category": "Non-Alcoholic",
        "subcategory": "carbonated_soft_drink",
        "confidence": 0.274,
        "detection_type": "exact_match",
        "context": "TNT dalawa Surf isang pack Coca Cola, pabili po"
      },
      {
        "brand": "TNT",
        "category": "Other Essentials",
        "subcategory": "unspecified",
        "confidence": 0.83,
        "detection_type": "exact_match",
        "context": "TNT dalawa Surf isang"
      }
    ],
    "implicitSignals": [],
    "detectionMethods": [
      "exact_match"
    ],
    "categoryBrandMapping": {
      "Laundry": {
        "branded": [
          {
            "brand": "Surf",
            "confidence": 0.83,
            "quantity": 1
          }
        ],
        "unbranded_volume": 0
      },
      "Non-Alcoholic": {
        "branded": [
          {
            "brand": "Coca-Cola",
            "confidence": 0.274,
            "quantity": 2
          }
        ],
        "unbranded_volume": 0
      },
      "Other Essentials": {
        "branded": [
          {
            "brand": "TNT",
            "confidence": 0.83,
            "quantity": 3
          }
        ],
        "unbranded_volume": 0
      }
    }
  },
  "items": [
    {
      "brandName": "Surf",
      "productName": "Surf Bar Kalamansi Large",
      "genericName": "Product",
      "localName": "surf",
      "sku": "SURF-BAR-KALAMANSI-360G",
      "quantity": 1,
      "unit": "pc",
      "unitPrice": 21.74,
      "totalPrice": 21.74,
      "category": "Laundry",
      "isUnbranded": false,
      "isBulk": false,
      "detectionMethod": "stt_brand_only",
      "confidence": 0.83,
      "brandConfidence": 0.88,
      "suggestedBrands": null,
      "notes": "STT: 'TNT dalawa Surf isang pack Coca'",
      "customerRequest": {
        "requestType": "branded",
        "specificBrand": true,
        "pointedToProduct": false,
        "acceptedSuggestion": false
      }
    },
    {
      "brandName": "Coca-Cola",
      "productName": "Coca-Cola 355ml Can",
      "genericName": "Product",
      "localName": "coke",
      "sku": "COKE-355ML",
      "quantity": 2,
      "unit": "pc",
      "unitPrice": 28.0,
      "totalPrice": 56.0,
      "category": "Non-Alcoholic",
      "isUnbranded": false,
      "isBulk": false,
      "detectionMethod": "stt_brand_only",
      "confidence": 0.274,
      "brandConfidence": 0.572,
      "suggestedBrands": null,
      "notes": "STT: 'TNT dalawa Surf isang pack Coca Cola, pabili po'",
      "customerRequest": {
        "requestType": "branded",
        "specificBrand": true,
        "pointedToProduct": false,
        "acceptedSuggestion": false
      }
    },
    {
      "brandName": "TNT",
      "productName": "TNT Load 100",
      "genericName": "Product",
      "localName": "tnt",
      "sku": "TNT-LOAD-100",
      "quantity": 3,
      "unit": "pc",
      "unitPrice": 100.0,
      "totalPrice": 300.0,
      "category": "Other Essentials",
      "isUnbranded": false,
      "isBulk": false,
      "detectionMethod": "stt_brand_only",
      "confidence": 0.83,
      "brandConfidence": 0.82,
      "suggestedBrands": null,
      "notes": "STT: 'TNT dalawa Surf isang'",
      "customerRequest": {
        "requestType": "branded",
        "specificBrand": true,
        "pointedToProduct": false,
        "acceptedSuggestion": false
      }
    }
  ],
  "totals": {
    "totalAmount": 377.74,
    "totalItems": 6,
    "brandedAmount": 377.74,
    "unbrandedAmount": 0.0,
    "brandedCount": 6,
    "unbrandedCount": 0,
    "uniqueBrandsCount": 3
  },
  "transactionContext": {
    "duration": 2.0,
    "paymentMethod": "cash",
    "timeOfDay": "unspecified",
    "dayType": "weekend",
    "audioTranscript": "TNT dalawa Surf isang pack Coca Cola, pabili po",
    "processingMethods": [
      "stt_transcription",
      "brand_detection",
      "fuzzy_matching",
      "pricing_lookup",
      "totals_calculation",
      "confidence_scoring"
    ]
  },
  "privacy": {
    "audioStored": false,
    "brandAnalysisOnly": true,
    "noFacialRecognition": true,
    "noImageProcessing": true,
    "dataRetentionDays": 30,
    "anonymizationLevel": "high",
    "consentTimestamp": "2025-09-13T16:51:01.222005.000Z"
  },
  "processingTime": 15.14,
  "edgeVersion": "v2.0.0-stt-only"
}