{
  "storeId": "103",
  "deviceId": "SCOUTPI-0003",
  "timestamp": "",
  "transactionId": "f6a12017-f5bb-4cb2-b60c-24416ea03310",
  "brandDetection": {
    "detectedBrands": {
      "Tide": 0.77,
      "Cream Silk": 0.224,
      "Palmolive": 0.77
    },
    "explicitMentions": [
      {
        "brand": "Tide",
        "category": "Laundry",
        "subcategory": "unspecified",
        "confidence": 0.77,
        "detection_type": "exact_match",
        "context": "tide na lang cream"
      },
      {
        "brand": "Cream Silk",
        "category": "Hair Care",
        "subcategory": "unspecified",
        "confidence": 0.224,
        "detection_type": "exact_match",
        "context": "tide na lang cream isa silk palmolive, kulang pa"
      },
      {
        "brand": "Palmolive",
        "category": "Hair Care",
        "subcategory": "unspecified",
        "confidence": 0.77,
        "detection_type": "exact_match",
        "context": "cream isa silk palmolive, kulang pa"
      }
    ],
    "implicitSignals": [],
    "detectionMethods": [
      "exact_match"
    ],
    "categoryBrandMapping": {
      "Laundry": {
        "branded": [
          {
            "brand": "Tide",
            "confidence": 0.77,
            "quantity": 1
          }
        ],
        "unbranded_volume": 0
      },
      "Hair Care": {
        "branded": [
          {
            "brand": "Cream Silk",
            "confidence": 0.224,
            "quantity": 1
          },
          {
            "brand": "Palmolive",
            "confidence": 0.77,
            "quantity": 1
          }
        ],
        "unbranded_volume": 0
      }
    }
  },
  "items": [
    {
      "brandName": "Tide",
      "productName": "Tide Detergent Bar",
      "genericName": "Product",
      "localName": "tide",
      "sku": "TIDE-BAR-125G",
      "quantity": 1,
      "unit": "pc",
      "unitPrice": 15.0,
      "totalPrice": 15.0,
      "category": "Laundry",
      "isUnbranded": false,
      "isBulk": false,
      "detectionMethod": "stt_brand_only",
      "confidence": 0.77,
      "brandConfidence": 0.82,
      "suggestedBrands": null,
      "notes": "STT: 'tide na lang cream'",
      "customerRequest": {
        "requestType": "branded",
        "specificBrand": true,
        "pointedToProduct": false,
        "acceptedSuggestion": false
      }
    },
    {
      "brandName": "Palmolive",
      "productName": "Palmolive Aloe & Olive",
      "genericName": "Product",
      "localName": "palmolive",
      "sku": "PALMOLIVE-ALOE-115G",
      "quantity": 1,
      "unit": "pc",
      "unitPrice": 25.0,
      "totalPrice": 25.0,
      "category": "Hair Care",
      "isUnbranded": false,
      "isBulk": false,
      "detectionMethod": "stt_brand_only",
      "confidence": 0.77,
      "brandConfidence": 0.82,
      "suggestedBrands": null,
      "notes": "STT: 'cream isa silk palmolive, kulang pa'",
      "customerRequest": {
        "requestType": "branded",
        "specificBrand": true,
        "pointedToProduct": false,
        "acceptedSuggestion": false
      }
    }
  ],
  "totals": {
    "totalAmount": 40.0,
    "totalItems": 2,
    "brandedAmount": 40.0,
    "unbrandedAmount": 0.0,
    "brandedCount": 2,
    "unbrandedCount": 0,
    "uniqueBrandsCount": 2
  },
  "transactionContext": {
    "duration": 2.0,
    "paymentMethod": "cash",
    "timeOfDay": "unspecified",
    "dayType": "weekend",
    "audioTranscript": "tide na lang cream isa silk palmolive, kulang pa",
    "processingMethods": [
      "stt_transcription",
      "brand_detection",
      "fuzzy_matching",
      "pricing_lookup",
      "totals_calculation",
      "confidence_scoring"
    ]
  },
  "privacy": {
    "audioStored": false,
    "brandAnalysisOnly": true,
    "noFacialRecognition": true,
    "noImageProcessing": true,
    "dataRetentionDays": 30,
    "anonymizationLevel": "high",
    "consentTimestamp": "2025-09-13T13:33:19.870360.000Z"
  },
  "processingTime": 15.5,
  "edgeVersion": "v2.0.0-stt-only"
}